{
    "solution": "${workspaceRoot}/Northwind.sln",
    "variables": {
        "MSBUILD": "C:/Program Files (x86)/Microsoft Visual Studio/2017/Enterprise/MSBuild/15.0/Bin/MSBuild.exe",
        "DEVENV": "C:/Program Files (x86)/Microsoft Visual Studio/2017/Enterprise/Common7/IDE/devenv.com"
    },
    "debugConfigurations": [
        {
            "name": "test",
            "cwd": "${workspaceRoot}",
            "program": "C:\\Program Files (x86)\\IIS Express\\iisexpress.exe",
            "args": [
                "/config:${workspaceRoot}\\.vs\\config\\applicationhost.config",
                "/site:Northwind.WebRole",
                "/apppool:Clr4IntegratedAppPool"
            ]
        }
    ] 
}